easy_config_hub/__init__.py
easy_config_hub/config.py
easy_config_hub/directories_config.py
easy_config_hub/enums_config.py
easy_config_hub/setting.py
easy_config_hub/type_enforcer.py
easy_config_hub-0.4.7.dist-info/WHEEL
easy_config_hub-0.4.7.dist-info/METADATA
easy_config_hub-0.4.7.dist-info/RECORD
