Metadata-Version: 2.3
Name: easy-config-hub
Version: 0.4.7
Summary: Add your description here
Author: Mudruk Artem
Author-email: Mudruk Artem <mudruk.arte@gmail.com>
Requires-Python: >=3.12
